black_forest_labs/__init__.py
black_forest_labs/client.py
black_forest_labs-1.0.0.dist-info/LICENSE.md
black_forest_labs-1.0.0.dist-info/METADATA
black_forest_labs-1.0.0.dist-info/WHEEL
black_forest_labs-1.0.0.dist-info/top_level.txt
black_forest_labs-1.0.0.dist-info/RECORD
