Metadata-Version: 2.1
Name: black-forest-labs
Version: 1.0.0
Summary: Unofficial Black Forest Labs API client
Requires-Python: >=3.8
License-File: LICENSE.md
Requires-Dist: httpx >=0.27.2
Requires-Dist: pydantic >=2.9.2
Requires-Dist: typing-extensions >=4.12.2
Provides-Extra: testing
Requires-Dist: pytest >=8.3.3 ; extra == 'testing'
Requires-Dist: respx >=0.21.1 ; extra == 'testing'
